fasttext_pybind.cpython-311-x86_64-linux-gnu.so
fasttext/FastText.py
fasttext/__init__.py
fasttext/tests/test_script.py
fasttext/tests/__init__.py
fasttext/tests/test_configurations.py
fasttext/util/util.py
fasttext/util/__init__.py
fasttext_numpy2-0.10.4.dist-info/LICENSE
fasttext_numpy2-0.10.4.dist-info/top_level.txt
fasttext_numpy2-0.10.4.dist-info/METADATA
fasttext_numpy2-0.10.4.dist-info/RECORD
fasttext_numpy2-0.10.4.dist-info/WHEEL
